{
  "$schema": "https://json-schema.org/draft/2020-12/schema",
  "$id": "https://raw.githubusercontent.com/istar-iscte/MPAI-AIH/refs/heads/main/diagrams/MPAI/Data/DeIdCriteria.json",
  "title": "DeIdCriteria",
  "description": "An object that represents the de-identification criteria",
  "type": "object",
  "properties": {
    "criteria": {
      "type": "string",
      "description": "The criteria to be applied to the de-identification"
    },
    "deIdentificationType": {
      "type": "string",
      "description": "The type of de-identification to be applied"
    },
    "deIdentificationValue": {
      "type": "string",
      "description": "The value to be applied to the de-identification"
    }
  },
  "required": ["criteria", "deIdentificationType", "deIdentificationValue"]
}